AUTHORS.md
LICENSE
MANIFEST.in
README.md
setup.cfg
setup.py
redisbox/__init__.py
redisbox/nose_plugin.py
redisbox/redisbox.py
redisbox/unittest.py
redisbox/utils.py
redisbox.egg-info/PKG-INFO
redisbox.egg-info/SOURCES.txt
redisbox.egg-info/dependency_links.txt
redisbox.egg-info/entry_points.txt
redisbox.egg-info/not-zip-safe
redisbox.egg-info/top_level.txt