Metadata-Version: 1.1
Name: redisbox
Version: 0.0.1
Summary: Run sandboxed Redis instance from a python application.
Home-page: http://github.com/ziadsawalha/redisbox
Author: Ziad Sawalha <ziad@sawalha.com>
Author-email: ziad@sawalha.com
License: Copyright 2014 Ziad Sawalha
